god_llm/__init__.py
god_llm/auth/__init__.py
god_llm/core/__init__.py
god_llm/core/base.py
god_llm/core/god.py
god_llm/core/question_evaluator.py
god_llm/plugins/__init__.py
god_llm/plugins/anthropic.py
god_llm/plugins/base.py
god_llm/plugins/exceptions.py
god_llm/plugins/groq.py
god_llm/plugins/openai.py
god_llm/templates/__init__.py
god_llm/templates/base.py
god_llm/templates/graph_templates.json
god_llm/templates/system_templates.json
god_llm/utils/__init__.py
god_llm/utils/base_format.py
god_llm/utils/tfidf.py
god_llm-0.1.1.dist-info/METADATA
god_llm-0.1.1.dist-info/WHEEL
god_llm-0.1.1.dist-info/RECORD
