Metadata-Version: 2.1
Name: god_llm
Version: 0.1.1
Summary: 
Author: mr-green1337
Author-email: islam.hachimi2003@gmail.com
Requires-Python: >=3.12,<4.0
Classifier: Programming Language :: Python :: 3
Classifier: Programming Language :: Python :: 3.12
Classifier: Programming Language :: Python :: 3.13
Provides-Extra: docs
Provides-Extra: testing
Requires-Dist: anthropic (>=0.36.2,<0.37.0)
Requires-Dist: groq (>=0.11.0,<0.12.0)
Requires-Dist: openai (>=1.52.0,<2.0.0)
Requires-Dist: pytest (>=8.3.3,<9.0.0) ; extra == "testing"
Requires-Dist: ruff (>=0.7.1,<0.8.0) ; extra == "testing"
